kmlplus/__init__.py
kmlplus/coordinates.py
kmlplus/paths.py
test/__init__.py
test/test_coordinates.py
test/test_paths.py
KMLPlus-2.1.0.dist-info/LICENSE
KMLPlus-2.1.0.dist-info/METADATA
KMLPlus-2.1.0.dist-info/WHEEL
KMLPlus-2.1.0.dist-info/top_level.txt
KMLPlus-2.1.0.dist-info/RECORD
