Metadata-Version: 2.1
Name: KMLPlus
Version: 2.1.0
Summary: A Python library for creating 3d floating polygons and circles in .kml for Google Earth.
Home-page: https://github.com/MHenderson1988/kmlplus
Author: Mark Henderson
Author-email: mark.henderson1988@gmail.com
License: UNKNOWN
Platform: UNKNOWN
Classifier: Programming Language :: Python :: 3
Classifier: License :: OSI Approved :: MIT License
Classifier: Operating System :: OS Independent
Requires-Python: >=3.8
